splitit_client/__init__.py
splitit_client/api_client.py
splitit_client/api_response.py
splitit_client/apis/__init__.py
splitit_client/apis/path_to_api.py
splitit_client/apis/paths/__init__.py
splitit_client/apis/paths/api_installmentplans.py
splitit_client/apis/paths/api_installmentplans_check_eligibility.py
splitit_client/apis/paths/api_installmentplans_initiate.py
splitit_client/apis/paths/api_installmentplans_installment_plan_number.py
splitit_client/apis/paths/api_installmentplans_installment_plan_number_refund.py
splitit_client/apis/paths/api_installmentplans_installment_plan_number_updateorder.py
splitit_client/apis/paths/api_installmentplans_installment_plan_number_verifyauthorization.py
splitit_client/apis/paths/api_installmentplans_ipn_legal.py
splitit_client/apis/paths/api_installmentplans_search.py
splitit_client/apis/paths/api_installmentplans_updateorder.py
splitit_client/apis/tag_to_api.py
splitit_client/apis/tags/__init__.py
splitit_client/apis/tags/installment_plan_api.py
splitit_client/apis/tags/installment_plan_api_generated.py
splitit_client/client.py
splitit_client/client.pyi
splitit_client/client_custom.py
splitit_client/configuration.py
splitit_client/exceptions.py
splitit_client/exceptions_base.py
splitit_client/model/__init__.py
splitit_client/model/address_data.py
splitit_client/model/address_data.pyi
splitit_client/model/address_data_model.py
splitit_client/model/address_data_model.pyi
splitit_client/model/authorization_model.py
splitit_client/model/authorization_model.pyi
splitit_client/model/bluesnap_vaulted_shopper_token.py
splitit_client/model/bluesnap_vaulted_shopper_token.pyi
splitit_client/model/card_brand.py
splitit_client/model/card_brand.pyi
splitit_client/model/card_data.py
splitit_client/model/card_data.pyi
splitit_client/model/card_type.py
splitit_client/model/card_type.pyi
splitit_client/model/check_installments_eligibility_request.py
splitit_client/model/check_installments_eligibility_request.pyi
splitit_web_python_sdk-3.0.9.dist-info/LICENSE
splitit_web_python_sdk-3.0.9.dist-info/METADATA
splitit_web_python_sdk-3.0.9.dist-info/WHEEL
splitit_web_python_sdk-3.0.9.dist-info/RECORD
